<?xml version="1.0" encoding="UTF-8"?>
<databaseChangeLog
        xmlns="http://www.liquibase.org/xml/ns/dbchangelog"
        xmlns:xsi="http://www.w3.org/2001/XMLSchema-instance"
        xmlns:pro="http://www.liquibase.org/xml/ns/pro"
        xsi:schemaLocation="http://www.liquibase.org/xml/ns/dbchangelog http://www.liquibase.org/xml/ns/dbchangelog/dbchangelog-4.6.xsd
    http://www.liquibase.org/xml/ns/pro http://www.liquibase.org/xml/ns/pro/liquibase-pro-4.6.xsd ">
   <property name="now" value="sysdate" dbms="oracle"/>
   <changeSet id="BOSS-5832_insert_llvalues.xml" author="Geraskina" >

    <insert tableName="dobjects_dbt">
        <column name="t_objecttype" value="4193" />
        <column name="t_name" value="Справоч статическ header IPS по формир. ОБ для ЮЛ" />
        <column name="t_code" value="BrkLEHead" />
        <column name="t_usernumber" value="0" />
        <column name="t_parentobjecttype" value="0" />
        <column name="t_servicemacro" valueComputed="chr(1)" />
        <column name="t_module" valueComputed="chr(1)" />
    </insert>

    <insert tableName="dllvalues_dbt">
        <column name="t_list" value="4193" />
        <column name="t_element" value="1" />
        <column name="t_code" value="1" />
        <column name="t_name" value="x-system-from" />
        <column name="t_flag" value="1" />
        <column name="t_note" value="SOFR" />
        <column name="t_reserve" valueComputed="chr(1)" />
    </insert>

    <insert tableName="dllvalues_dbt">
        <column name="t_list" value="4193" />
        <column name="t_element" value="2" />
        <column name="t_code" value="2" />
        <column name="t_name" value="x-system-to" />
        <column name="t_flag" value="2" />
        <column name="t_note" value="NDBOLE" />
        <column name="t_reserve" valueComputed="chr(1)" />
    </insert>

    <insert tableName="dllvalues_dbt">
        <column name="t_list" value="4193" />
        <column name="t_element" value="3" />
        <column name="t_code" value="3" />
        <column name="t_name" value="x-template-name" />
        <column name="t_flag" value="3" />
        <column name="t_note" value="legal-entity-report" />
        <column name="t_reserve" valueComputed="chr(1)" />
    </insert>

    <insert tableName="dllvalues_dbt">
        <column name="t_list" value="4193" />
        <column name="t_element" value="4" />
        <column name="t_code" value="4" />
        <column name="t_name" value="x-bucket-name" />
        <column name="t_flag" value="4" />
        <column name="t_note" value="legal-entity-report" />
        <column name="t_reserve" valueComputed="chr(1)" />
    </insert>

    <insert tableName="dllvalues_dbt">
        <column name="t_list" value="4193" />
        <column name="t_element" value="5" />
        <column name="t_code" value="5" />
        <column name="t_name" value="x-template-type" />
        <column name="t_flag" value="5" />
        <column name="t_note" value="jrxml" />
        <column name="t_reserve" valueComputed="chr(1)" />
    </insert>

    <insert tableName="dllvalues_dbt">
        <column name="t_list" value="4193" />
        <column name="t_element" value="6" />
        <column name="t_code" value="6" />
        <column name="t_name" value="x-output-type" />
        <column name="t_flag" value="6" />
        <column name="t_note" value="PDF" />
        <column name="t_reserve" valueComputed="chr(1)" />
    </insert>

    <insert tableName="dllvalues_dbt">
        <column name="t_list" value="4193" />
        <column name="t_element" value="7" />
        <column name="t_code" value="7" />
        <column name="t_name" value="x-service-name" />
        <column name="t_flag" value="7" />
        <column name="t_note" value="GenerateLegalEntityReport" />
        <column name="t_reserve" valueComputed="chr(1)" />
    </insert>
                  
    <insert tableName="dobjects_dbt">
        <column name="t_objecttype" value="4192" />
        <column name="t_name" value="Справоч статическ header IPS по статусу ОБ для ЮЛ" />
        <column name="t_code" value="StLEHead" />
        <column name="t_usernumber" value="0" />
        <column name="t_parentobjecttype" value="0" />
        <column name="t_servicemacro" valueComputed="chr(1)" />
        <column name="t_module" valueComputed="chr(1)" />
    </insert>

    <insert tableName="dllvalues_dbt">
        <column name="t_list" value="4192" />
        <column name="t_element" value="1" />
        <column name="t_code" value="1" />
        <column name="t_name" value="x-system-from" />
        <column name="t_flag" value="1" />
        <column name="t_note" value="SOFR" />
        <column name="t_reserve" valueComputed="chr(1)" />
    </insert>

    <insert tableName="dllvalues_dbt">
        <column name="t_list" value="4192" />
        <column name="t_element" value="2" />
        <column name="t_code" value="2" />
        <column name="t_name" value="x-system-to" />
        <column name="t_flag" value="2" />
        <column name="t_note" value="NDBOLE" />
        <column name="t_reserve" valueComputed="chr(1)" />
    </insert>

    <insert tableName="dllvalues_dbt">
        <column name="t_list" value="4192" />
        <column name="t_element" value="3" />
        <column name="t_code" value="6" />
        <column name="t_name" value="x-output-type" />
        <column name="t_flag" value="3" />
        <column name="t_note" value="PDF" />
        <column name="t_reserve" valueComputed="chr(1)" />
    </insert>

    <insert tableName="dllvalues_dbt">
        <column name="t_list" value="4192" />
        <column name="t_element" value="4" />
        <column name="t_code" value="7" />
        <column name="t_name" value="x-service-name" />
        <column name="t_flag" value="4" />
        <column name="t_note" value="SendFileNotification" />
        <column name="t_reserve" valueComputed="chr(1)" />
    </insert>
    
   </changeSet>

</databaseChangeLog>
