<?xml version="1.0" encoding="UTF-8"?>
<TableList xmlns:xsi="http://www.w3.org/2001/XMLSchema-instance"
    xsi:schemaLocation="http://www.softlab.ru fmtxml.xsd"
    xmlns="http://www.softlab.ru">
  <Table T_NAME="d_fo07_tmp" T_OWNER="" T_CACHESIZE="0" T_PKIDX="0" T_BLOBTYPE="BT_BLOB_NO" T_BLOBLEN="0" 
TF_TEMPORARY="true" TF_STRUCT="false" T_COMMENT="Таблица для создания ЗР по F07 и O07">
    <Field T_NAME="t_id_fm_fo07" T_TYPE="FT_INT32" T_SIZE="4" T_OUTLEN="0" T_DECPOINT="0" T_HIDDEN="false" T_COMMENT="ID_FM_F07 или ID_FM_F07"/>
    <Field T_NAME="t_id_mb_requisites" T_TYPE="FT_INT32" T_SIZE="4" T_OUTLEN="0" T_DECPOINT="0" T_HIDDEN="false" T_COMMENT="ID_MB_REQUISITES"/>
    <Field T_NAME="t_id_processing_log" T_TYPE="FT_INT32" T_SIZE="4" T_OUTLEN="0" T_DECPOINT="0" T_HIDDEN="false" T_COMMENT="ID_PROCESSING_LOG"/>
    <Field T_NAME="t_contract" T_TYPE="FT_STRING" T_SIZE="26" T_OUTLEN="0" T_DECPOINT="0" T_HIDDEN="false" T_COMMENT="CONTRACT"/>
    <Field T_NAME="t_startdate" T_TYPE="FT_DATE" T_SIZE="4" T_OUTLEN="0" T_DECPOINT="0" T_HIDDEN="false" T_COMMENT="DATE1"/>
    <Field T_NAME="t_executiondate" T_TYPE="FT_DATE" T_SIZE="4" T_OUTLEN="0" T_DECPOINT="0" T_HIDDEN="false" T_COMMENT="EXECUTION"/>
    <Field T_NAME="t_low" T_TYPE="FT_NUMERIC" T_SIZE="16" T_OUTLEN="0" T_DECPOINT="0" T_HIDDEN="false" T_COMMENT="LOW"/>
    <Field T_NAME="t_high" T_TYPE="FT_NUMERIC" T_SIZE="16" T_OUTLEN="0" T_DECPOINT="0" T_HIDDEN="false" T_COMMENT="HIGH"/>
    <Field T_NAME="t_settl" T_TYPE="FT_NUMERIC" T_SIZE="16" T_OUTLEN="0" T_DECPOINT="0" T_HIDDEN="false" T_COMMENT="SETTL"/>
    <Field T_NAME="t_tick_price" T_TYPE="FT_NUMERIC" T_SIZE="16" T_OUTLEN="0" T_DECPOINT="0" T_HIDDEN="false" T_COMMENT="TICK_PRICE"/>
    <Field T_NAME="t_tick" T_TYPE="FT_NUMERIC" T_SIZE="16" T_OUTLEN="0" T_DECPOINT="0" T_HIDDEN="false" T_COMMENT="TICK"/>
    <Field T_NAME="t_base_contr" T_TYPE="FT_STRING" T_SIZE="26" T_OUTLEN="0" T_DECPOINT="0" T_HIDDEN="false" T_COMMENT="BASE_FUT или FUT_CONTR"/>
    <Field T_NAME="t_namecontr" T_TYPE="FT_STRING" T_SIZE="26" T_OUTLEN="0" T_DECPOINT="0" T_HIDDEN="false" T_COMMENT="NAME"/>
    <Field T_NAME="t_is_percent" T_TYPE="FT_INT16" T_SIZE="2" T_OUTLEN="0" T_DECPOINT="0" T_HIDDEN="false" T_COMMENT="IS_PERCENT"/>
    <Field T_NAME="t_settl_rur" T_TYPE="FT_NUMERIC" T_SIZE="16" T_OUTLEN="0" T_DECPOINT="0" T_HIDDEN="false" T_COMMENT="SETTL_RUR"/>
    <Field T_NAME="t_lot_volume" T_TYPE="FT_INT32" T_SIZE="4" T_OUTLEN="0" T_DECPOINT="0" T_HIDDEN="false" T_COMMENT="LOT_VOLUME"/>
    <Field T_NAME="t_type_exec" T_TYPE="FT_INT16" T_SIZE="2" T_OUTLEN="0" T_DECPOINT="0" T_HIDDEN="false" T_COMMENT="TYPE_EXEC"/>
    <Field T_NAME="t_l_tradeday" T_TYPE="FT_DATE" T_SIZE="4" T_OUTLEN="0" T_DECPOINT="0" T_HIDDEN="false" T_COMMENT="L_TRADEDAY"/>
    <Field T_NAME="t_strike" T_TYPE="FT_NUMERIC" T_SIZE="16" T_OUTLEN="0" T_DECPOINT="0" T_HIDDEN="false" T_COMMENT="STRIKE"/>
    <Field T_NAME="t_put" T_TYPE="FT_CHR" T_SIZE="1" T_OUTLEN="0" T_DECPOINT="0" T_HIDDEN="false" T_COMMENT="PUT"/>
    <Field T_NAME="t_evrop" T_TYPE="FT_CHR" T_SIZE="1" T_OUTLEN="0" T_DECPOINT="0" T_HIDDEN="false" T_COMMENT="EVROP"/>
    <Field T_NAME="t_theorprice" T_TYPE="FT_NUMERIC" T_SIZE="16" T_OUTLEN="0" T_DECPOINT="0" T_HIDDEN="false" T_COMMENT="THEORPRICE"/>
    <Field T_NAME="t_fut_type" T_TYPE="FT_INT16" T_SIZE="2" T_OUTLEN="0" T_DECPOINT="0" T_HIDDEN="false" T_COMMENT="FUT_TYPE"/>
    <Field T_NAME="t_uniqcodepfi" T_TYPE="FT_STRING" T_SIZE="36" T_OUTLEN="0" T_DECPOINT="0" T_HIDDEN="false" T_COMMENT="Уникальный код ЗР ПИ"/>
    <Field T_NAME="t_uniqcodecp" T_TYPE="FT_STRING" T_SIZE="41" T_OUTLEN="0" T_DECPOINT="0" T_HIDDEN="false" T_COMMENT="Уникальный код ЗР курса РЦ"/>
    <Field T_NAME="t_uniqcodecpg" T_TYPE="FT_STRING" T_SIZE="41" T_OUTLEN="0" T_DECPOINT="0" T_HIDDEN="false" T_COMMENT="Уникальный код ЗР курса РЦ для главы Г"/>
    <Field T_NAME="t_uniqcodeminp" T_TYPE="FT_STRING" T_SIZE="41" T_OUTLEN="0" T_DECPOINT="0" T_HIDDEN="false" T_COMMENT="Уникальный код ЗР курса мин. цена"/>
    <Field T_NAME="t_uniqcodemaxp" T_TYPE="FT_STRING" T_SIZE="41" T_OUTLEN="0" T_DECPOINT="0" T_HIDDEN="false" T_COMMENT="Уникальный код ЗР курса макс. цена"/>
    <Field T_NAME="t_uniqcodetp" T_TYPE="FT_STRING" T_SIZE="41" T_OUTLEN="0" T_DECPOINT="0" T_HIDDEN="false" T_COMMENT="Уникальный код ЗР курса ТЦ"/>
    <Field T_NAME="t_uniqcodeminsp" T_TYPE="FT_STRING" T_SIZE="41" T_OUTLEN="0" T_DECPOINT="0" T_HIDDEN="false" T_COMMENT="Уникальный код ЗР курса ст. мин. шага"/>
    <Field T_NAME="t_objectidpfi" T_TYPE="FT_INT32" T_SIZE="4" T_OUTLEN="0" T_DECPOINT="0" T_HIDDEN="false" T_COMMENT="ID объекта шлюза ПИ"/>
    <Field T_NAME="t_objectidcp" T_TYPE="FT_INT32" T_SIZE="4" T_OUTLEN="0" T_DECPOINT="0" T_HIDDEN="false" T_COMMENT="ID объекта шлюза курса РЦ"/>
    <Field T_NAME="t_objectidcpg" T_TYPE="FT_INT32" T_SIZE="4" T_OUTLEN="0" T_DECPOINT="0" T_HIDDEN="false" T_COMMENT="ID объекта шлюза курса РЦ для главы Г"/>
    <Field T_NAME="t_objectidminp" T_TYPE="FT_INT32" T_SIZE="4" T_OUTLEN="0" T_DECPOINT="0" T_HIDDEN="false" T_COMMENT="ID объекта шлюза курса мин. цена"/>
    <Field T_NAME="t_objectidmaxp" T_TYPE="FT_INT32" T_SIZE="4" T_OUTLEN="0" T_DECPOINT="0" T_HIDDEN="false" T_COMMENT="ID объекта шлюза курса макс. цена"/>
    <Field T_NAME="t_objectidtp" T_TYPE="FT_INT32" T_SIZE="4" T_OUTLEN="0" T_DECPOINT="0" T_HIDDEN="false" T_COMMENT="ID объекта шлюза курса ТЦ"/>
    <Field T_NAME="t_objectidminsp" T_TYPE="FT_INT32" T_SIZE="4" T_OUTLEN="0" T_DECPOINT="0" T_HIDDEN="false" T_COMMENT="ID объекта шлюза курса ст. мин. шага"/>
    <Field T_NAME="t_imp_date" T_TYPE="FT_DATE" T_SIZE="4" T_OUTLEN="0" T_DECPOINT="0" T_HIDDEN="false" T_COMMENT="Дата импорта"/>
    <Field T_NAME="t_fi_kind" T_TYPE="FT_INT16" T_SIZE="2" T_OUTLEN="0" T_DECPOINT="0" T_HIDDEN="false" T_COMMENT="Вид ФИ"/>
    <Field T_NAME="t_section" T_TYPE="FT_STRING" T_SIZE="51" T_OUTLEN="0" T_DECPOINT="0" T_HIDDEN="false" T_COMMENT="Секция рынка"/>
    <Field T_NAME="t_close" T_TYPE="FT_NUMERIC" T_SIZE="16" T_OUTLEN="0" T_DECPOINT="0" T_HIDDEN="false" T_COMMENT="CLOSE"/>
    <Field T_NAME="t_uniqcodeclp" T_TYPE="FT_STRING" T_SIZE="41" T_OUTLEN="0" T_DECPOINT="0" T_HIDDEN="false" T_COMMENT="Уникальный код ЗР курса цена закрытия"/>
    <Field T_NAME="t_objectidclp" T_TYPE="FT_INT32" T_SIZE="4" T_OUTLEN="0" T_DECPOINT="0" T_HIDDEN="false" T_COMMENT="ID объекта шлюза курса цена закрытия"/>
    <Key T_KEYNUM="0" TF_DUPLICATES="false" TF_MODIFIABLE="true" TF_BINARY="false" TF_NULLVAL="false" TF_SUPPLEMENT="false" TF_EXTENDED="true" TF_MANUAL="false">
      <Segment T_FIELD="t_id_fm_fo07" TF_ALTERNATE="false" TF_DESCENDING="false" TF_LOCAL="false" T_TYPE="Einteger" T_NULLVAL="0" T_ISREAL="true" T_COMMENT=""/>
    </Key>
  </Table>
</TableList>
