<?xml version="1.0" encoding="UTF-8"?>   
<databaseChangeLog     
       xmlns="http://www.liquibase.org/xml/ns/dbchangelog"    
       xmlns:xsi="http://www.w3.org/2001/XMLSchema-instance"   
       xmlns:pro="http://www.liquibase.org/xml/ns/pro"         
       xsi:schemaLocation="http://www.liquibase.org/xml/ns/dbchangelog http://www.liquibase.org/xml/ns/dbchangelog/dbchangelog-4.6.xsd 
    http://www.liquibase.org/xml/ns/pro http://www.liquibase.org/xml/ns/pro/liquibase-pro-4.6.xsd">
  
  <include file="113.2/113.2_BOSS-7954_update_mb_sem02.xml"/>
  <include file="113.2/113.2_BOSS-7954_update_mb_sem03.xml"/>
  <include file="113.2/113.2_BOSS-7954_update_mb_sem21.xml"/>
  <include file="113.2/113.2_BOSS-7954_update_mb_eqm06.xml"/>
  <include file="113.2/113.2_BOSS-7954_update_mb_eqm6c.xml"/>

  <changeSet id="113.2_BOSS-7954_update_nform.sql" context="prod" author="Zhits"> 
    <sqlFile encoding="cp866" 
           endDelimiter="/" 
       path="./113.2/113.2_BOSS-7954_update_nform.sql" 
       splitStatements="true" 
       stripComments="false"/> 
  </changeSet>

</databaseChangeLog> 
